{
  "distribution": null,
  "kalai": {
    "outcome": [
      "864_80"
    ],
    "utility": [
      [
        0.9231582204815055,
        0.2951342553097289
      ]
    ]
  },
  "load_path": null,
  "name": "0000945S1327",
  "nash": {
    "outcome": [
      "864_80"
    ],
    "utility": [
      [
        0.9231582204815055,
        0.2951342553097289
      ]
    ]
  },
  "opposition": 0.7077608267961979,
  "pareto_front": [
    {
      "outcome": [
        "864_80"
      ],
      "utility": [
        0.9231582204815055,
        0.2951342553097289
      ]
    },
    {
      "outcome": [
        "541_403"
      ],
      "utility": [
        0.9259216735391773,
        0.28452037227149113
      ]
    },
    {
      "outcome": [
        "181_763"
      ],
      "utility": [
        0.9115127911217338,
        0.2971361767178274
      ]
    },
    {
      "outcome": [
        "547_397"
      ],
      "utility": [
        0.8994246983527234,
        0.29921419470666655
      ]
    },
    {
      "outcome": [
        "711_233"
      ],
      "utility": [
        0.9345735417202976,
        0.25129023771873393
      ]
    },
    {
      "outcome": [
        "28_916"
      ],
      "utility": [
        0.9358935499520862,
        0.24622034411485313
      ]
    },
    {
      "outcome": [
        "623_321"
      ],
      "utility": [
        0.9361633986202066,
        0.2451839081263702
      ]
    },
    {
      "outcome": [
        "410_534"
      ],
      "utility": [
        0.870563325910376,
        0.30417564332092106
      ]
    },
    {
      "outcome": [
        "84_860"
      ],
      "utility": [
        0.9405914838052258,
        0.22817649846306123
      ]
    },
    {
      "outcome": [
        "716_228"
      ],
      "utility": [
        0.9443326580587065,
        0.213807379421262
      ]
    },
    {
      "outcome": [
        "553_391"
      ],
      "utility": [
        0.8291425209606861,
        0.3112961361432724
      ]
    },
    {
      "outcome": [
        "433_511"
      ],
      "utility": [
        0.828329260137753,
        0.31143594071393266
      ]
    },
    {
      "outcome": [
        "114_830"
      ],
      "utility": [
        0.824429664624183,
        0.31210630532655126
      ]
    },
    {
      "outcome": [
        "490_454"
      ],
      "utility": [
        0.9552681367150335,
        0.1718063433974446
      ]
    },
    {
      "outcome": [
        "647_297"
      ],
      "utility": [
        0.9576296205143291,
        0.16273634571001022
      ]
    },
    {
      "outcome": [
        "170_774"
      ],
      "utility": [
        0.9585331889492673,
        0.15926591596673906
      ]
    },
    {
      "outcome": [
        "834_110"
      ],
      "utility": [
        0.9599372025426723,
        0.15387337418893446
      ]
    },
    {
      "outcome": [
        "830_114"
      ],
      "utility": [
        0.9627599075659075,
        0.14303191593260894
      ]
    }
  ],
  "size": 945,
  "social_welfare": {
    "outcome": [
      "864_80"
    ],
    "utility": [
      [
        0.9231582204815055,
        0.2951342553097289
      ]
    ]
  },
  "src_path": "environment/scenarios/training_src/anac2024/0000945S1327"
}